treasuryio/__init__.py
treasuryio/query.py
treasuryio/tweetbot.py
treasuryio-0.0.4.dist-info/DESCRIPTION.rst
treasuryio-0.0.4.dist-info/METADATA
treasuryio-0.0.4.dist-info/RECORD
treasuryio-0.0.4.dist-info/WHEEL
treasuryio-0.0.4.dist-info/metadata.json
treasuryio-0.0.4.dist-info/top_level.txt
