Metadata-Version: 2.0
Name: treasuryio
Version: 0.0.4
Summary: Query treasury.io through Python, returning Pandas DataFrames
Home-page: https://github.com/csvsoundsystem/pytreasuryio.git
Author: Thomas Levine
Author-email: Thomas Levine
License: MIT
Platform: UNKNOWN
Classifier: Intended Audience :: Developers
Classifier: License :: OSI Approved :: MIT License
Classifier: Programming Language :: Python :: 2.7
Classifier: Programming Language :: SQL
Classifier: Topic :: Database :: Front-Ends
Requires-Dist: pandas
Requires-Dist: tweepy
